GoogleAds
