Metadata-Version: 2.1
Name: Google-Ads-Transparency-Scraper
Version: 1.6.0
Summary: A scraper for getting Ads from Google Ads Transparency
Home-page: https://github.com/faniAhmed/GoogleAdsTransparencyScraper
Download-URL: https://github.com/faniAhmed/GoogleAdsTransparencyScraper/archive/refs/tags/v1.6.0.tar.gz
Author: Farhan Ahmed
Author-email: jattfarhan10@gmail.com
License: Securely Incorporation
Keywords: Google,Transparency,Scraper,API,Google Ads,Ads,Google Transparency,Google Transparency Scraper,Google Ads Scraper
Platform: any
Classifier: Development Status :: 5 - Production/Stable
Classifier: Environment :: Console
Classifier: Intended Audience :: Developers
Classifier: License :: Free for non-commercial use
Classifier: Natural Language :: Urdu
Classifier: Operating System :: OS Independent
Classifier: Programming Language :: Python :: 3
